mtb/core/Namespace.py
mtb/core/Signal.py
mtb/core/SubprocessPool.py
mtb/core/__init__.py
mtb/core/_utils.py
mtb/core/cli_tools.py
mtb/core/cmd.py
mtb/core/context.py
mtb/core/decorators.py
mtb/core/enum.py
mtb/core/format.py
mtb/core/log.py
mtb/core/naming.py
mtb/core/observer.py
mtb/core/patcher.py
mtb/core/pip.py
mtb/core/thread.py
mtb/core/watcher.py
mtb/core/atoms/__init__.py
mtb/core/atoms/options.py
mtb/core/atoms/random.py
mtb/core/atoms/vector3.py
mtb/core/fixtures/PathsFixture.py
mtb/core/fixtures/__init__.py
mtb/core/message/client.py
mtb/core/message/server.py
mtb/core/os/_CrossPlatformPath.py
mtb/core/os/__init__.py
mtb/core/os/_base_methods.py
mtb/core/raytracer/camera.py
mtb/core/raytracer/ray.py
mtb_core-0.1.0.dist-info/METADATA
mtb_core-0.1.0.dist-info/WHEEL
mtb_core-0.1.0.dist-info/top_level.txt
mtb_core-0.1.0.dist-info/RECORD
