Metadata-Version: 2.1
Name: mtb-core
Version: 0.1.0
Summary: Shared library
Author-email: Mel Massadian <mel@melmassadian.com>
Requires-Python: >=3.9
Requires-Dist: numpy >=1.21
Requires-Dist: keyboard <0.14.0,>=0.13.5
Requires-Dist: msgpack <2.0.0,>=1.0.5
Requires-Dist: pyzmq <26.0.0,>=25.1.1
Requires-Dist: rich <14.0.0,>=13.7.0
Requires-Dist: rich-argparse <1.4.0,>=1.3.0
Requires-Dist: watchdog <4.0.0,>=3.0.0
Requires-Dist: aiofiles <24.0.0,>=23.2.1
Requires-Dist: virtualenv
Provides-Extra: dev
Requires-Dist: black ; extra == 'dev'
Requires-Dist: isort ; extra == 'dev'
Requires-Dist: pylint ; extra == 'dev'
Requires-Dist: pyright ; extra == 'dev'
Requires-Dist: pytest ; extra == 'dev'
